[{"title":"heise online News","description":"Nachrichten nicht nur aus der Welt der Computer","url":"https://www.heise.de/newsticker/heise-atom.xml"},{"title":"Caschys Blog","description":"Web, Software, Hardware, Mobile Computing & Co","url":"https://feeds2.feedburner.com/stadt-bremerhaven/dqXM"},{"title":"Mobilegeeks.de","description":"Mobile News, Smartphones, Tablets, Ultrabooks, Apps","url":"https://www.mobilegeeks.de/feed/"},{"title":"GIGA","description":"GIGA News Feed","url":"http://www.giga.de/feed/"},{"title":"Golem.de","description":"IT-News fuer Profis","url":"https://rss.golem.de/rss.php"},{"title":"t3n RSS Feed - News","description":"t3n digital pioneers - News","url":"https://t3n.de/rss.xml"}]